LICENSE
MANIFEST.in
README.md
quicktest.py
settings_test.py
setup.py
django_vkontakte_photos.egg-info/PKG-INFO
django_vkontakte_photos.egg-info/SOURCES.txt
django_vkontakte_photos.egg-info/dependency_links.txt
django_vkontakte_photos.egg-info/not-zip-safe
django_vkontakte_photos.egg-info/requires.txt
django_vkontakte_photos.egg-info/top_level.txt
vkontakte_photos/__init__.py
vkontakte_photos/__init__.pyc
vkontakte_photos/admin.py
vkontakte_photos/admin.pyc
vkontakte_photos/factories.py
vkontakte_photos/factories.pyc
vkontakte_photos/models.py
vkontakte_photos/models.pyc
vkontakte_photos/parser.py
vkontakte_photos/parser.pyc
vkontakte_photos/tests.py
vkontakte_photos/tests.pyc
vkontakte_photos/migrations/0001_initial.py
vkontakte_photos/migrations/0001_initial.pyc
vkontakte_photos/migrations/0002_auto__chg_field_photo_height__chg_field_photo_width.py
vkontakte_photos/migrations/0002_auto__chg_field_photo_height__chg_field_photo_width.pyc
vkontakte_photos/migrations/0003_auto__add_field_photo_src_xxbig.py
vkontakte_photos/migrations/0003_auto__add_field_photo_src_xxbig.pyc
vkontakte_photos/migrations/0004_auto__add_field_photo_comments.py
vkontakte_photos/migrations/0004_auto__add_field_photo_comments.pyc
vkontakte_photos/migrations/0005_auto__chg_field_album_updated.py
vkontakte_photos/migrations/0005_auto__chg_field_album_updated.pyc
vkontakte_photos/migrations/0006_auto__add_field_photo_tags.py
vkontakte_photos/migrations/0006_auto__add_field_photo_tags.pyc
vkontakte_photos/migrations/0007_auto__chg_field_photo_user.py
vkontakte_photos/migrations/0007_auto__chg_field_photo_user.pyc
vkontakte_photos/migrations/0008_auto.py
vkontakte_photos/migrations/0008_auto.pyc
vkontakte_photos/migrations/0009_auto.py
vkontakte_photos/migrations/0009_auto.pyc
vkontakte_photos/migrations/0010_auto.py
vkontakte_photos/migrations/0010_auto.pyc
vkontakte_photos/migrations/0011_auto__add_comment.py
vkontakte_photos/migrations/0011_auto__add_comment.pyc
vkontakte_photos/migrations/0012_auto__chg_field_album_created.py
vkontakte_photos/migrations/0012_auto__chg_field_album_created.pyc
vkontakte_photos/migrations/0013_auto__add_field_photo_likes_count__add_field_photo_comments_count__add.py
